Metadata-Version: 1.1
Name: menace
Version: 0.1.3
Summary: A metagenomics pipeline to estimate relative cell periods.
Home-page: https://www.github.com/SysBio/menace/
Author: Daniel Hermansson
Author-email: hedani@chalmers.se
License: MIT
Keywords: systems biology research
Platform: UNKNOWN
Classifier: Development Status :: 3 - Alpha
Classifier: Intended Audience :: Science/Research
Classifier: Topic :: Scientific/Engineering :: Bio-Informatics
Classifier: License :: OSI Approved :: MIT License
Classifier: Programming Language :: Python :: 2
Classifier: Programming Language :: Python :: 2.7
